[
    {
        "title": "Ananas Track 6 - Low Top",
        "color": "Triple Black",
        "image": "https://ananas.vn/wp-content/uploads/pro_track6_A6T003_1-500x500.jpg",
        "current_price": "990.000 VN"
    },
    {
        "title": "Ananas Track 6 - Low Top",
        "color": "Triple White",
        "image": "https://ananas.vn/wp-content/uploads/pro_track6_A6T002_1-500x500.jpg",
        "current_price": "990.000 VN"
    },
    {
        "title": "Ananas Track 6 OG - Low Top",
        "color": "70s White",
        "image": "https://ananas.vn/wp-content/uploads/pro_track6_A6T001_1-500x500.jpg",
        "current_price": "990.000 VN"
    },
    {
        "title": "Ananas Track 6 Suede - Low Top",
        "color": "Meadow",
        "image": "https://ananas.vn/wp-content/uploads/pro_A6T004_1_1-500x500.jpg",
        "current_price": "990.000 VN"
    },
    {
        "title": "Creas Flip-Flap - High Top",
        "color": "Magenta-Snorkel Blue",
        "image": "https://ananas.vn/wp-content/uploads/pro_creas_A61084_1-500x500.jpg",
        "current_price": "690.000 VN"
    },
    {
        "title": "Basas Mono - High Top",
        "color": "All White",
        "image": "https://ananas.vn/wp-content/uploads/pro_basas_A61078_1-500x500.jpg",
        "current_price": "520.000 VN"
    },
    {
        "title": "Basas Suede - Low Top",
        "color": "Black",
        "image": "https://ananas.vn/wp-content/uploads/pro_basas_A61068_1-500x500.jpg",
        "current_price": "580.000 VN"
    },
    {
        "title": "Basas Mono - Low Top",
        "color": "Taos Taupe",
        "image": "https://ananas.vn/wp-content/uploads/stu_basas_A61006_1-500x500.jpg",
        "current_price": "450.000 VN"
    },
    {
        "title": "Basas PU Mono v.2 - Low Top",
        "color": "White",
        "image": "https://ananas.vn/wp-content/uploads/pro_basas_A61069_1-500x500.jpg",
        "current_price": "520.000 VN"
    },
    {
        "title": "Basas Mono - Low Top",
        "color": "Dark Grey",
        "image": "https://ananas.vn/wp-content/uploads/stu_basas_A61007_1-500x500.jpg",
        "current_price": "450.000 VN"
    },
    {
        "title": "Basas New Simple Life - High Top",
        "color": "Taupe",
        "image": "https://ananas.vn/wp-content/uploads/pro_basas_A61080_1-500x500.jpg",
        "current_price": "520.000 VN"
    },
    {
        "title": "Basas Mono-Black - High Top",
        "color": "All Black",
        "image": "https://ananas.vn/wp-content/uploads/stu_basas_A61018_1-500x500.jpg",
        "current_price": "490.000 VN"
    },
    {
        "title": "Basas Bumper Gum - Low Top",
        "color": "Offwhite",
        "image": "https://ananas.vn/wp-content/uploads/stu_basas_A61008_1_1-500x500.jpg",
        "current_price": "450.000 VN"
    },
    {
        "title": "Basas Bumper Gum - Low Top",
        "color": "Offwhite/Gum",
        "image": "https://ananas.vn/wp-content/uploads/pro_basas_A61071_1-500x500.jpg",
        "current_price": "450.000 VN"
    },
    {
        "title": "Basas New Simple Life - Low Top",
        "color": "Black",
        "image": "https://ananas.vn/wp-content/uploads/stu_basas_A61000_1-500x500.jpg",
        "current_price": "420.000 VN"
    },
    {
        "title": "Basas Bumper Gum - High Top",
        "color": "Offwhite/Gum",
        "image": "https://ananas.vn/wp-content/uploads/pro_basas_A61020_1-500x500.jpg",
        "current_price": "490.000 VN"
    },
    {
        "title": "Basas Black Lace -  Low Top",
        "color": "Dark Grey",
        "image": "https://ananas.vn/wp-content/uploads/pro_basas_A61067_1-500x500.jpg",
        "current_price": "450.000 VN"
    },
    {
        "title": "Basas Bumper Gum - Low Top",
        "color": "Offwhite/Gum",
        "image": "https://ananas.vn/wp-content/uploads/pro_basas_A61073_1-500x500.jpg",
        "current_price": "450.000 VN"
    },
    {
        "title": "Basas Black Lace -  Low Top",
        "color": "Dark Grey",
        "image": "https://ananas.vn/wp-content/uploads/pro_basas_A61074_1-500x500.jpg",
        "current_price": "320.000 VN"
    },
    {
        "title": "Basas New Simple Life - Slip On",
        "color": "White",
        "image": "https://ananas.vn/wp-content/uploads/stu_basas_A61023_1-500x500.jpg",
        "current_price": "420.000 VN"
    },
    {
        "title": "Basas Mono-Black - Low Top",
        "color": "All Black",
        "image": "https://ananas.vn/wp-content/uploads/stu_basas_A61001_1-500x500.jpg",
        "current_price": "420.000 VN"
    },
    {
        "title": "Basas Bumper Gum - Slip On",
        "color": "Offwhite/Gum",
        "image": "https://ananas.vn/wp-content/uploads/stu_basas_A61024_1-500x500.jpg",
        "current_price": "450.000 VN"
    },
    {
        "title": "Basas New Simple Life - Low Top",
        "color": "White",
        "image": "https://ananas.vn/wp-content/uploads/stu_basas_A61002_1-500x500.jpg",
        "current_price": "420.000 VN"
    },
    {
        "title": "Basas Mono Black - High Top",
        "color": "All Black",
        "image": "https://ananas.vn/wp-content/uploads/pro_basas_A61076_1-500x500.jpg",
        "current_price": "490.000 VN"
    },
    {
        "title": "Basas New Familiar - Low Top",
        "color": "White",
        "image": "https://ananas.vn/wp-content/uploads/stu_basas_A61014_11-500x500.jpg",
        "current_price": "420.000 VN"
    },
    {
        "title": "Urbas Irrelevant - Slip On",
        "color": "Storm/A.Gold",
        "image": "https://ananas.vn/wp-content/uploads/pro_A61108_1-500x500.jpg",
        "current_price": "490.000 VN"
    },
    {
        "title": "Urbas Irrelevant - Slip On",
        "color": "Antarctica/Red Orange",
        "image": "https://ananas.vn/wp-content/uploads/pro_A61109_1-500x500.jpg",
        "current_price": "490.000 VN"
    },
    {
        "title": "Basas New Simple Life - Slip On",
        "color": "White",
        "image": "https://ananas.vn/wp-content/uploads/stu_basas_A61023_1-500x500.jpg",
        "current_price": "420.000 VN"
    },
    {
        "title": "Basas Bumper Gum - Slip On",
        "color": "Offwhite/Gum",
        "image": "https://ananas.vn/wp-content/uploads/stu_basas_A61024_1-500x500.jpg",
        "current_price": "450.000 VN"
    },
    {
        "title": "Vintas Yesterday - Slip On",
        "color": "Taupe Leather",
        "image": "https://ananas.vn/wp-content/uploads/pro_vintas_A61047_1-500x500.jpg",
        "current_price": "330.000 VN"
    },
    {
        "title": "Vintas Bleached Sand - Slip On",
        "color": "Bleached Sand",
        "image": "https://ananas.vn/wp-content/uploads/pro_vintas_A61046_1-500x500.jpg",
        "current_price": "450.000 VN"
    },
    {
        "title": "Urbas The Ocean - Slip On",
        "color": "Living Coral",
        "image": "https://ananas.vn/wp-content/uploads/pro_urbas_A40004_1-1-500x500.jpg",
        "current_price": "530.000 VN"
    },
    {
        "title": "Urbas The Ocean - Slip On",
        "color": "Poseidon",
        "image": "https://ananas.vn/wp-content/uploads/pro_urbas_A21004_1-1-500x500.jpg",
        "current_price": "390.000 VN"
    },
    {
        "title": "Basas New Simple Life - Slip On",
        "color": "Black",
        "image": "https://ananas.vn/wp-content/uploads/stu_basas_A61021_1-500x500.jpg",
        "current_price": "420.000 VN"
    },
    {
        "title": "Basas New Simple Life - Slip On",
        "color": "Dark Grey",
        "image": "https://ananas.vn/wp-content/uploads/pro_basas_A61081_1-500x500.jpg",
        "current_price": "320.000 VN"
    },
    {
        "title": "Basas Mono-Black - Slip On",
        "color": "All Black",
        "image": "https://ananas.vn/wp-content/uploads/stu_basas_A61022_1-500x500.jpg",
        "current_price": "420.000 VN"
    },
    {
        "title": "Basas New Simple Life - Slip On",
        "color": "Chilli Pepper",
        "image": "https://ananas.vn/wp-content/uploads/pro_basas_A61082_1-500x500.jpg",
        "current_price": "320.000 VN"
    },
    {
        "title": "Urbas Pure Red - Slip On",
        "color": "Bloody Snow",
        "image": "https://ananas.vn/wp-content/uploads/pro_urbas_A61064_1-1-500x500.jpg",
        "current_price": "350.000 VN"
    },
    {
        "title": "Vintas Yesterday - Slip On",
        "color": "Black Leather",
        "image": "https://ananas.vn/wp-content/uploads/pro_vintas_A61048_1-500x500.jpg",
        "current_price": "310.000 VN"
    },
    {
        "title": "Vintas Yesterday - Slip On",
        "color": "Moonstruck Pirate",
        "image": "https://ananas.vn/wp-content/uploads/pro_vintas_A61049_1-500x500.jpg",
        "current_price": "480.000 VN"
    },
    {
        "title": "Urbas Unsettling - High Top",
        "color": "Starlight/Lavender",
        "image": "https://ananas.vn/wp-content/uploads/pro_A61106_1-500x500.jpg",
        "current_price": "550.000 VN"
    },
    {
        "title": "Urbas Unsettling - High Top",
        "color": "Insignia/Sulphur",
        "image": "https://ananas.vn/wp-content/uploads/pro_A61107_1-500x500.jpg",
        "current_price": "550.000 VN"
    },
    {
        "title": "Urbas Unsettling - Low Top",
        "color": "Starlight/Lavender",
        "image": "https://ananas.vn/wp-content/uploads/pro_A61102_1-500x500.jpg",
        "current_price": "490.000 VN"
    },
    {
        "title": "Urbas Unsettling - Low Top",
        "color": "Insignia/Sulphur",
        "image": "https://ananas.vn/wp-content/uploads/pro_A61103_1-500x500.jpg",
        "current_price": "490.000 VN"
    },
    {
        "title": "Urbas Irrelevant - Low Top",
        "color": "Storm/A.Gold",
        "image": "https://ananas.vn/wp-content/uploads/pro_A61104_1-500x500.jpg",
        "current_price": "550.000 VN"
    },
    {
        "title": "Urbas Irrelevant - Slip On",
        "color": "Storm/A.Gold",
        "image": "https://ananas.vn/wp-content/uploads/pro_A61108_1-500x500.jpg",
        "current_price": "490.000 VN"
    },
    {
        "title": "Urbas Irrelevant - Slip On",
        "color": "Antarctica/Red Orange",
        "image": "https://ananas.vn/wp-content/uploads/pro_A61109_1-500x500.jpg",
        "current_price": "490.000 VN"
    },
    {
        "title": "Urbas Bloody - Low Top",
        "color": "Haute Red",
        "image": "https://ananas.vn/wp-content/uploads/pro_urbas_A61054_1-500x500.jpg",
        "current_price": "440.000 VN"
    },
    {
        "title": "Urbas Inversion - Low Top",
        "color": "N-Gold Flame",
        "image": "https://ananas.vn/wp-content/uploads/pro_urbas_A61059_1-500x500.jpg",
        "current_price": "320.000 VN"
    },
    {
        "title": "Urbas Pineapple or Ananas - Low Top",
        "color": "Pineapple Peel",
        "image": "https://ananas.vn/wp-content/uploads/pro_A61086_1-500x500.jpg",
        "current_price": "490.000 VN"
    },
    {
        "title": "Urbas Inversion - High Top",
        "color": "N-Gold Flame",
        "image": "https://ananas.vn/wp-content/uploads/pro_urbas_A61063_1-1-500x500.jpg",
        "current_price": "370.000 VN"
    },
    {
        "title": "Urbas Pineapple or Ananas - Low Top",
        "color": "Pineapple Leaves",
        "image": "https://ananas.vn/wp-content/uploads/pro_A61087_1-500x500.jpg",
        "current_price": "490.000 VN"
    },
    {
        "title": "Urbas Inversion - Low Top",
        "color": "Navy Citrus",
        "image": "https://ananas.vn/wp-content/uploads/pro_urbas_A61056_1-500x500.jpg",
        "current_price": "420.000 VN"
    },
    {
        "title": "Urbas Pineapple or Ananas - Low Top",
        "color": "Pineapple Poker",
        "image": "https://ananas.vn/wp-content/uploads/pro_A61088_1-500x500.jpg",
        "current_price": "490.000 VN"
    },
    {
        "title": "Urbas The Gang - Low Top",
        "color": "Haute Black",
        "image": "https://ananas.vn/wp-content/uploads/pro_urbas_A61050_1-1-500x500.jpg",
        "current_price": "450.000 VN"
    },
    {
        "title": "Urbas Inversion - Low Top",
        "color": "C-Navy Blue",
        "image": "https://ananas.vn/wp-content/uploads/pro_urbas_A61058_1-1.jpg",
        "current_price": "320.000 VN"
    },
    {
        "title": "Urbas Corluray - Low Top",
        "color": "Deep Green",
        "image": "https://ananas.vn/wp-content/uploads/pro_A61089_1_1-500x500.jpg",
        "current_price": "590.000 VN"
    },
    {
        "title": "Urbas The Gang - Low Top",
        "color": "Ceramic Black",
        "image": "https://ananas.vn/wp-content/uploads/pro_urbas_A61051_1-1-500x500.jpg",
        "current_price": "450.000 VN"
    },
    {
        "title": "Urbas Inversion - High Top",
        "color": "Navy Citrus",
        "image": "https://ananas.vn/wp-content/uploads/pro_urbas_A61060_1-500x500.jpg",
        "current_price": "510.000 VN"
    },
    {
        "title": "Urbas Corluray - Low Top",
        "color": "Faded pink",
        "image": "https://ananas.vn/wp-content/uploads/pro_A61090_1_1jpg-500x500.jpg",
        "current_price": "590.000 VN"
    },
    {
        "title": "Urbas Unsettling - Low Top",
        "color": "Starlight/Lavender",
        "image": "https://ananas.vn/wp-content/uploads/pro_A61102_1-500x500.jpg",
        "current_price": "490.000 VN"
    },
    {
        "title": "Urbas Unsettling - High Top",
        "color": "Starlight/Lavender",
        "image": "https://ananas.vn/wp-content/uploads/pro_A61106_1-500x500.jpg",
        "current_price": "550.000 VN"
    },
    {
        "title": "Urbas Unsettling - High Top",
        "color": "Insignia/Sulphur",
        "image": "https://ananas.vn/wp-content/uploads/pro_A61107_1-500x500.jpg",
        "current_price": "550.000 VN"
    },
    {
        "title": "Urbas Unsettling - Low Top",
        "color": "Insignia/Sulphur",
        "image": "https://ananas.vn/wp-content/uploads/pro_A61103_1-500x500.jpg",
        "current_price": "490.000 VN"
    },
    {
        "title": "Vintas New Bleached Sand - Low Top",
        "color": "Roasted Sand",
        "image": "https://ananas.vn/wp-content/uploads/pro_A61100_1-500x500.jpg",
        "current_price": "550.000 VN"
    },
    {
        "title": "Urbas Irrelevant - Slip On",
        "color": "Antarctica/Red Orange",
        "image": "https://ananas.vn/wp-content/uploads/pro_A61109_1-500x500.jpg",
        "current_price": "490.000 VN"
    },
    {
        "title": "Ananas Track 6 - Low Top",
        "color": "Triple White",
        "image": "https://ananas.vn/wp-content/uploads/pro_track6_A6T002_1-500x500.jpg",
        "current_price": "990.000 VN"
    },
    {
        "title": "Urbas Irrelevant - Slip On",
        "color": "Storm/A.Gold",
        "image": "https://ananas.vn/wp-content/uploads/pro_A61108_1-500x500.jpg",
        "current_price": "490.000 VN"
    },
    {
        "title": "Ananas Track 6 - Low Top",
        "color": "Triple Black",
        "image": "https://ananas.vn/wp-content/uploads/pro_track6_A6T003_1-500x500.jpg",
        "current_price": "990.000 VN"
    },
    {
        "title": "Urbas Irrelevant - Low Top",
        "color": "Storm/A.Gold",
        "image": "https://ananas.vn/wp-content/uploads/pro_A61104_1-500x500.jpg",
        "current_price": "550.000 VN"
    },
    {
        "title": "Vintas Mister - High Top",
        "color": "Chocolate Brown",
        "image": "https://ananas.vn/wp-content/uploads/pro_A61101_1_1-500x500.jpg",
        "current_price": "610.000 VN"
    },
    {
        "title": "Basas New Simple Life - Slip On",
        "color": "White",
        "image": "https://ananas.vn/wp-content/uploads/stu_basas_A61023_1-500x500.jpg",
        "current_price": "420.000 VN"
    },
    {
        "title": "Basas Bumper Gum - Low Top",
        "color": "Offwhite",
        "image": "https://ananas.vn/wp-content/uploads/stu_basas_A61008_1_1-500x500.jpg",
        "current_price": "450.000 VN"
    },
    {
        "title": "Basas Bumper Gum - Low Top",
        "color": "Black/Gum",
        "image": "https://ananas.vn/wp-content/uploads/pro_basas_A61065_1-500x500.jpg",
        "current_price": "450.000 VN"
    },
    {
        "title": "Basas Bumper Gum - Slip On",
        "color": "Offwhite/Gum",
        "image": "https://ananas.vn/wp-content/uploads/stu_basas_A61024_1-500x500.jpg",
        "current_price": "450.000 VN"
    },
    {
        "title": "Basas New Simple Life - Low Top",
        "color": "Black",
        "image": "https://ananas.vn/wp-content/uploads/stu_basas_A61000_1-500x500.jpg",
        "current_price": "420.000 VN"
    },
    {
        "title": "Basas New Simple Life - High Top",
        "color": "Taupe",
        "image": "https://ananas.vn/wp-content/uploads/pro_basas_A61080_1-500x500.jpg",
        "current_price": "520.000 VN"
    },
    {
        "title": "Basas New Familiar - Low Top",
        "color": "White",
        "image": "https://ananas.vn/wp-content/uploads/stu_basas_A61014_11-500x500.jpg",
        "current_price": "420.000 VN"
    },
    {
        "title": "Basas Suede - Low Top",
        "color": "Black",
        "image": "https://ananas.vn/wp-content/uploads/pro_basas_A61068_1-500x500.jpg",
        "current_price": "580.000 VN"
    },
    {
        "title": "Basas Mono-Black - Low Top",
        "color": "All Black",
        "image": "https://ananas.vn/wp-content/uploads/stu_basas_A61001_1-500x500.jpg",
        "current_price": "420.000 VN"
    },
    {
        "title": "Vintas New Bleached Sand - Low Top",
        "color": "Roasted Sand",
        "image": "https://ananas.vn/wp-content/uploads/pro_A61100_1-500x500.jpg",
        "current_price": "550.000 VN"
    },
    {
        "title": "Vintas Mister - High Top",
        "color": "Chocolate Brown",
        "image": "https://ananas.vn/wp-content/uploads/pro_A61101_1_1-500x500.jpg",
        "current_price": "610.000 VN"
    },
    {
        "title": "Vintas Earth - Low Top",
        "color": "Dark Olive",
        "image": "https://ananas.vn/wp-content/uploads/pro_vintas_A61033_1-500x500.jpg",
        "current_price": "580.000 VN"
    },
    {
        "title": "Vintas New Bleached Sand - Low Top",
        "color": "Bleached Sand",
        "image": "https://ananas.vn/wp-content/uploads/pro_vintas_A61025_1-500x500.jpg",
        "current_price": "465.000 VN"
    },
    {
        "title": "Vintas Mister - Low Top",
        "color": "Slate Carafe",
        "image": "https://ananas.vn/wp-content/uploads/pro_vintas_A61038_1-1-500x500.jpg",
        "current_price": "465.000 VN"
    },
    {
        "title": "Vintas Mister - Low Top",
        "color": "Narcissuede",
        "image": "https://ananas.vn/wp-content/uploads/pro_vintas_A61039_1-500x500.jpg",
        "current_price": "580.000 VN"
    },
    {
        "title": "Vintas Saigon 1980s - Low Top",
        "color": "Vin Black",
        "image": "https://ananas.vn/wp-content/uploads/pro_vintas_A61032_1-500x500.jpg",
        "current_price": "480.000 VN"
    },
    {
        "title": "Vintas Bleached Sand - Low Top",
        "color": "Bleached Sand",
        "image": "https://ananas.vn/wp-content/uploads/pro_vintas_A61036_1-500x500.jpg",
        "current_price": "465.000 VN"
    },
    {
        "title": "Vintas The New Military - Low Top",
        "color": "Capulet Olive",
        "image": "https://ananas.vn/wp-content/uploads/pro_vintas_A61026_1-500x500.jpg",
        "current_price": "465.000 VN"
    },
    {
        "title": "Vintas Saigon 1980s - Low Top",
        "color": "Vin Cordovan",
        "image": "https://ananas.vn/wp-content/uploads/pro_vintas_A61029_1-500x500.jpg",
        "current_price": "480.000 VN"
    },
    {
        "title": "Vintas The New Military - High Top",
        "color": "Capulet Olive",
        "image": "https://ananas.vn/wp-content/uploads/pro_vintas_A61043_1-500x500.jpg",
        "current_price": "495.000 VN"
    },
    {
        "title": "Vintas Saigon 1980s - Low Top",
        "color": "Dark Denim",
        "image": "https://ananas.vn/wp-content/uploads/pro_vintas_A61031_1-500x500.jpg",
        "current_price": "480.000 VN"
    },
    {
        "title": "Vintas Earth - Low Top",
        "color": "Goat",
        "image": "https://ananas.vn/wp-content/uploads/pro_vintas_A61034_1-500x500.jpg",
        "current_price": "580.000 VN"
    },
    {
        "title": "Vintas Yesterday - Low Top",
        "color": "Moonstruck Pirate",
        "image": "https://ananas.vn/wp-content/uploads/pro_vintas_A61035_1-1-500x500.jpg",
        "current_price": "480.000 VN"
    },
    {
        "title": "Vintas Yesterday - High Top",
        "color": "Moonstruck Pirate",
        "image": "https://ananas.vn/wp-content/uploads/pro_vintas_A61044_1-500x500.jpg",
        "current_price": "550.000 VN"
    },
    {
        "title": "Vintas Saigon 1980s - Low Top",
        "color": "Sedona Sage",
        "image": "https://ananas.vn/wp-content/uploads/pro_vintas_A61030_1-500x500.jpg",
        "current_price": "480.000 VN"
    },
    {
        "title": "Vintas Earth - High Top",
        "color": "Goat",
        "image": "https://ananas.vn/wp-content/uploads/pro_vintas_A61042_1-500x500.jpg",
        "current_price": "495.000 VN"
    },
    {
        "title": "Vintas Yesterday - Slip On",
        "color": "Taupe Leather",
        "image": "https://ananas.vn/wp-content/uploads/pro_vintas_A61047_1-500x500.jpg",
        "current_price": "330.000 VN"
    },
    {
        "title": "Vintas Saigon 1980s - High Top",
        "color": "Dark Denim",
        "image": "https://ananas.vn/wp-content/uploads/pro_vintas_A61041_1-500x500.jpg",
        "current_price": "495.000 VN"
    },
    {
        "title": "Vintas Yesterday - Slip On",
        "color": "Black Leather",
        "image": "https://ananas.vn/wp-content/uploads/pro_vintas_A61048_1-500x500.jpg",
        "current_price": "310.000 VN"
    }
]